neji/__init__.py
neji-0.0.1.0.dist-info/LICENSE.txt
neji-0.0.1.0.dist-info/METADATA
neji-0.0.1.0.dist-info/WHEEL
neji-0.0.1.0.dist-info/top_level.txt
neji-0.0.1.0.dist-info/RECORD
