Metadata-Version: 2.1
Name: neji
Version: 0.0.1.0
Summary: Cloud Storage and GUI Framework
Home-page: UNKNOWN
Author: Viraj Neji
Author-email: unanneji@gmail.com
License: UNKNOWN
Platform: UNKNOWN
Classifier: Programming Language :: Python :: 3
Classifier: License :: OSI Approved :: MIT License
Classifier: Operating System :: OS Independent
Requires-Dist: requests
Requires-Dist: whichcraft
